knuckles/__init__.py
knuckles/_api.py
knuckles/_bookmarks.py
knuckles/_browsing.py
knuckles/_chat.py
knuckles/_internet_radio.py
knuckles/_jukebox.py
knuckles/_lists.py
knuckles/_media_annotation.py
knuckles/_media_library_scanning.py
knuckles/_media_retrieval.py
knuckles/_playlists.py
knuckles/_podcast.py
knuckles/_searching.py
knuckles/_sharing.py
knuckles/_subsonic.py
knuckles/_system.py
knuckles/_user_management.py
knuckles/exceptions.py
knuckles/py.typed
knuckles/models/__init__.py
knuckles/models/_album.py
knuckles/models/_artist.py
knuckles/models/_artist_index.py
knuckles/models/_bookmark.py
knuckles/models/_chat_message.py
knuckles/models/_contributor.py
knuckles/models/_cover_art.py
knuckles/models/_genre.py
knuckles/models/_internet_radio_station.py
knuckles/models/_jukebox.py
knuckles/models/_lyrics.py
knuckles/models/_model.py
knuckles/models/_music_directory.py
knuckles/models/_music_folder.py
knuckles/models/_now_playing_entry.py
knuckles/models/_play_queue.py
knuckles/models/_playlist.py
knuckles/models/_podcast.py
knuckles/models/_replay_gain.py
knuckles/models/_scan_status.py
knuckles/models/_search_result.py
knuckles/models/_share.py
knuckles/models/_song.py
knuckles/models/_starred_content.py
knuckles/models/_system.py
knuckles/models/_user.py
knuckles/models/_video.py
knuckles-1.2.0.dist-info/LICENSE.txt
knuckles-1.2.0.dist-info/METADATA
knuckles-1.2.0.dist-info/WHEEL
knuckles-1.2.0.dist-info/top_level.txt
knuckles-1.2.0.dist-info/RECORD
