Metadata-Version: 2.1
Name: knuckles
Version: 1.2.0
Summary: A Subsonic/OpenSubsonic API wrapper for Python.
Author-email: "Jorge \"Kutu\" Dobón Blanco" <code@dobon.dev>
Project-URL: Documentation, https://kutu-dev.github.io/knuckles/
Project-URL: Repository, https://github.com/kutu-dev/knuckles
Project-URL: Issues, https://github.com/kutu-dev/knuckles/issues
Project-URL: Changelog, https://github.com/kutu-dev/knuckles/blob/master/CHANGELOG.md
Keywords: api-wrapper,api,wrapper,library,subsonic,opensubsonic
Classifier: Development Status :: 5 - Production/Stable
Classifier: Programming Language :: Python
Classifier: Programming Language :: Python :: 3
Classifier: Programming Language :: Python :: 3.11
Classifier: Programming Language :: Python :: 3.12
Classifier: Programming Language :: Python :: 3.13
Classifier: Intended Audience :: Developers
Classifier: License :: OSI Approved :: Apache Software License
Classifier: Environment :: Web Environment
Classifier: Operating System :: OS Independent
Classifier: Topic :: Internet
Classifier: Topic :: Internet :: WWW/HTTP
Classifier: Topic :: Multimedia
Classifier: Topic :: Software Development :: Libraries
Classifier: Topic :: Software Development :: Libraries :: Python Modules
Classifier: Typing :: Typed
Requires-Python: >=3.11.0
License-File: LICENSE.txt
Requires-Dist: requests>=2.32.3
Requires-Dist: python-dateutil>=2.8.2
Provides-Extra: dev
Requires-Dist: pip-tools>=7.4.1; extra == "dev"
Provides-Extra: check
Requires-Dist: types-requests; extra == "check"
Requires-Dist: types-python-dateutil; extra == "check"
Requires-Dist: ruff>=0.1.2; extra == "check"
Requires-Dist: mypy>=1.4.1; extra == "check"
Provides-Extra: tests
Requires-Dist: pytest>=7.4.0; extra == "tests"
Requires-Dist: responses>=0.23.1; extra == "tests"
Provides-Extra: docs
Requires-Dist: mkdocs>=1.5.3; extra == "docs"
Requires-Dist: mkdocs-material>=9.5.18; extra == "docs"
Requires-Dist: mkdocstrings[python]>=0.24.3; extra == "docs"
Requires-Dist: mkdocs-gen-files>=0.5.0; extra == "docs"
Requires-Dist: pymdown-extensions>=10.8.0; extra == "docs"
Requires-Dist: mkdocs-literate-nav>=0.6.1; extra == "docs"
